SuomiGeoData/__init__.py
SuomiGeoData/core.py
SuomiGeoData/paituli.py
SuomiGeoData/syke.py
SuomiGeoData/data/example_area.cpg
SuomiGeoData/data/example_area.dbf
SuomiGeoData/data/example_area.prj
SuomiGeoData/data/example_area.shp
SuomiGeoData/data/example_area.shx
SuomiGeoData/data/nls_dem_index.cpg
SuomiGeoData/data/nls_dem_index.dbf
SuomiGeoData/data/nls_dem_index.prj
SuomiGeoData/data/nls_dem_index.shp
SuomiGeoData/data/nls_dem_index.shx
SuomiGeoData/data/nls_td_index.cpg
SuomiGeoData/data/nls_td_index.dbf
SuomiGeoData/data/nls_td_index.prj
SuomiGeoData/data/nls_td_index.shp
SuomiGeoData/data/nls_td_index.shx
SuomiGeoData/data/tdb_metadata.xlsx
SuomiGeoData-1.1.1.dist-info/LICENSE.txt
SuomiGeoData-1.1.1.dist-info/METADATA
SuomiGeoData-1.1.1.dist-info/WHEEL
SuomiGeoData-1.1.1.dist-info/top_level.txt
SuomiGeoData-1.1.1.dist-info/RECORD
