Metadata-Version: 2.1
Name: SuomiGeoData
Version: 1.1.1
Summary: Downloading and extracting geospatial data from Finland, that is Suomi.
Author-email: Debasish Pal <bestdebasish@gmail.com>
Project-URL: Homepage, https://github.com/debpal/SuomiGeoData
Project-URL: Documentation, http://suomigeodata.readthedocs.io/
Keywords: Paituli,Syke,Topography,Data download,Data analysis
Classifier: Development Status :: 4 - Beta
Classifier: Programming Language :: Python :: 3.10
Classifier: Programming Language :: Python :: 3.11
Classifier: Programming Language :: Python :: 3.12
Classifier: License :: OSI Approved :: MIT License
Classifier: Operating System :: OS Independent
Classifier: Intended Audience :: Education
Classifier: Intended Audience :: Science/Research
Classifier: Topic :: Scientific/Engineering :: GIS
Classifier: Topic :: Scientific/Engineering :: Hydrology
Requires-Python: >=3.10
License-File: LICENSE.txt
Requires-Dist: geopandas
Requires-Dist: rasterio
Requires-Dist: requests
Requires-Dist: openpyxl
Requires-Dist: xlsxwriter
